llama_index/embeddings/nomic/__init__.py
llama_index/embeddings/nomic/base.py
llama_index_embeddings_nomic-0.7.1.dist-info/METADATA
llama_index_embeddings_nomic-0.7.1.dist-info/WHEEL
llama_index_embeddings_nomic-0.7.1.dist-info/licenses/LICENSE
llama_index_embeddings_nomic-0.7.1.dist-info/RECORD
