Metadata-Version: 2.4
Name: llama-index-embeddings-nomic
Version: 0.7.1
Summary: llama-index embeddings nomic integration
Author-email: Jared Van Bortel <jared@nomic.ai>, Zach Nussbaum <zach@nomic.ai>
License-Expression: MIT
License-File: LICENSE
Requires-Python: <4.0,>=3.9
Requires-Dist: einops<0.8,>=0.7.0
Requires-Dist: llama-index-core<0.15,>=0.13.0
Requires-Dist: llama-index-embeddings-huggingface<0.7,>=0.6.0
Requires-Dist: nomic<4,>=3.0.30
